rockstar/RockStar.py
rockstar/__init__.py
rockstar/commit-messages.json
rockstar-0.6.dist-info/LICENSE
rockstar-0.6.dist-info/METADATA
rockstar-0.6.dist-info/WHEEL
rockstar-0.6.dist-info/entry_points.txt
rockstar-0.6.dist-info/top_level.txt
rockstar-0.6.dist-info/RECORD
