Metadata-Version: 2.1
Name: rockstar
Version: 0.6
Summary: Makes you a Rockstar programmer in 2 minutes
Home-page: https://github.com/avinassh/rockstar/
Author: Avinash Sajjanshetty
Author-email: hi@avi.im
License: MIT
Platform: UNKNOWN
Classifier: Development Status :: 3 - Alpha
Classifier: License :: OSI Approved :: MIT License
Classifier: Operating System :: POSIX
Classifier: Intended Audience :: Developers
Classifier: Natural Language :: English
Classifier: Operating System :: OS Independent
Classifier: Programming Language :: Python
Classifier: Programming Language :: Python :: 3
Classifier: Programming Language :: Python :: 3.3
Classifier: Programming Language :: Python :: 3.4
Classifier: Programming Language :: Python :: 3.5
Classifier: Topic :: Internet
Classifier: Topic :: Software Development :: Libraries
Classifier: Topic :: Software Development :: Libraries :: Python Modules
Classifier: Topic :: Utilities
Requires-Dist: click (>=7.1.2)
Requires-Dist: gitpython (>=3.1.14)
